chaac/__init__.py
chaac/chaac_packet.py
chaac/chaacdb.py
chaac/packets.py
chaac-0.23.dist-info/METADATA
chaac-0.23.dist-info/WHEEL
chaac-0.23.dist-info/top_level.txt
chaac-0.23.dist-info/RECORD
