Metadata-Version: 2.1
Name: chaac
Version: 0.23
Summary: Chaac Library
Home-page: https://github.com/alvarop/chaac
Author: Alvaro Prieto
Author-email: source@alvaroprieto.com
License: MIT
Platform: UNKNOWN
Classifier: Programming Language :: Python :: 3
Classifier: License :: OSI Approved :: MIT License
Classifier: Operating System :: OS Independent
Requires-Python: >=3.6
